[{"name": "com.foobnix.pro.pdf.reader"}, {"name": "com.manimarank.spell4wiki"}, {"name": "org.koitharu.kotatsu"}, {"name": "org.koreader.launcher.fdroid"}, {"name": "org.ligi.passandroid"}, {"name": "name.bresciani.marco.tkcompanionapp"}, {"name": "de.taz.android.app.free"}, {"name": "com.nononsenseapps.feeder"}, {"name": "com.jiaqifeng.hacki"}, {"name": "com.cosmos.unreddit"}, {"name": "com.saverio.wordoftheday_en"}, {"name": "org.decsync.sparss.floss"}, {"name": "io.gresse.hugo.anecdote"}, {"name": "com.tttdevs.stncbookmarks"}, {"name": "de.beowulf.libretranslater"}, {"name": "com.ero.kinoko"}, {"name": "com.quinncasey.paperless_share"}, {"name": "dev.atajan.lingva_android"}, {"name": "net.nightwhistler.pageturner"}, {"name": "io.davidar.fabularium"}, {"name": "de.tap.easy_xkcd"}, {"name": "net.kervala.comicsreader"}, {"name": "it.angrydroids.epub3reader"}, {"name": "org.ligi.survivalmanual"}, {"name": "cx.hell.android.pdfview"}, {"name": "eu.bauerj.paperless_app"}, {"name": "italian.said.fran.theitaliansaid"}, {"name": "com.github.jameshnsears.quoteunquote"}, {"name": "buet.rafi.dictionary"}, {"name": "software.mdev.bookstracker"}, {"name": "de.geeksfactory.opacclient"}, {"name": "com.mareksebera.simpledilbert"}, {"name": "com.newsblur"}, {"name": "com.github.niccokunzmann.hanumanchalisa"}, {"name": "org.bibledit.android"}, {"name": "eu.prismsw.lampshade"}, {"name": "de.reimardoeffinger.quickdic"}, {"name": "com.jorgecastillo.kanadrill"}, {"name": "com.iven.xdafeedreader"}, {"name": "org.opengemara.shiurim"}, {"name": "com.concept1tech.instalate"}, {"name": "itkach.aard2"}, {"name": "com.hyperionics.fbreader.plugin.tts_plus"}, {"name": "nodomain.vanous.blitztypekeyboard"}, {"name": "ml.docilealligator.infinityforreddit"}, {"name": "eu.kanade.tachiyomi"}, {"name": "com.krawieck.lemmur"}, {"name": "com.olam"}, {"name": "de.eknoes.inofficialgolem"}, {"name": "com.fullscreen"}]